{
  "series": {
    "stormlight-archive": {
      "title": "The Stormlight Archive",
      "author": "Brandon Sanderson",
      "books": {
        "way-of-kings": {
          "title": "The Way of Kings",
          "chapters": 75,
          "published": "2010"
        },
        "words-of-radiance": {
          "title": "Words of Radiance", 
          "chapters": 89,
          "published": "2014"
        },
        "oathbringer": {
          "title": "Oathbringer",
          "chapters": 122,
          "published": "2017"
        },
        "rhythm-of-war": {
          "title": "Rhythm of War",
          "chapters": 117,
          "published": "2020"
        }
      }
    },
    "mistborn": {
      "title": "Mistborn",
      "author": "Brandon Sanderson",
      "books": {
        "final-empire": {
          "title": "The Final Empire",
          "chapters": 38,
          "published": "2006"
        },
        "well-of-ascension": {
          "title": "The Well of Ascension",
          "chapters": 59,
          "published": "2007"
        },
        "hero-of-ages": {
          "title": "The Hero of Ages",
          "chapters": 82,
          "published": "2008"
        }
      }
    },
    "dune": {
      "title": "Dune",
      "author": "Frank Herbert",
      "books": {
        "dune": {
          "title": "Dune",
          "chapters": 48,
          "published": "1965"
        },
        "dune-messiah": {
          "title": "Dune Messiah",
          "chapters": 35,
          "published": "1969"
        },
        "children-of-dune": {
          "title": "Children of Dune",
          "chapters": 64,
          "published": "1976"
        }
      }
    },
    "harry-potter": {
      "title": "Harry Potter",
      "author": "J.K. Rowling",
      "books": {
        "philosophers-stone": {
          "title": "The Philosopher's Stone",
          "chapters": 17,
          "published": "1997"
        },
        "chamber-of-secrets": {
          "title": "The Chamber of Secrets",
          "chapters": 18,
          "published": "1998"
        },
        "prisoner-of-azkaban": {
          "title": "The Prisoner of Azkaban",
          "chapters": 22,
          "published": "1999"
        },
        "goblet-of-fire": {
          "title": "The Goblet of Fire",
          "chapters": 37,
          "published": "2000"
        },
        "order-of-phoenix": {
          "title": "The Order of the Phoenix",
          "chapters": 38,
          "published": "2003"
        },
        "half-blood-prince": {
          "title": "The Half-Blood Prince",
          "chapters": 30,
          "published": "2005"
        },
        "deathly-hallows": {
          "title": "The Deathly Hallows",
          "chapters": 37,
          "published": "2007"
        }
      }
    },
    "chronicles-narnia": {
      "title": "Chronicles of Narnia",
      "author": "C.S. Lewis",
      "books": {
        "lion-witch-wardrobe": {
          "title": "The Lion, the Witch and the Wardrobe",
          "chapters": 17,
          "published": "1950"
        },
        "prince-caspian": {
          "title": "Prince Caspian",
          "chapters": 15,
          "published": "1951"
        },
        "voyage-dawn-treader": {
          "title": "The Voyage of the Dawn Treader",
          "chapters": 16,
          "published": "1952"
        },
        "silver-chair": {
          "title": "The Silver Chair",
          "chapters": 16,
          "published": "1953"
        },
        "horse-and-his-boy": {
          "title": "The Horse and His Boy",
          "chapters": 15,
          "published": "1954"
        },
        "magicians-nephew": {
          "title": "The Magician's Nephew",
          "chapters": 15,
          "published": "1955"
        },
        "last-battle": {
          "title": "The Last Battle",
          "chapters": 16,
          "published": "1956"
        }
      }
    },
    "lord-of-rings": {
      "title": "Lord of the Rings",
      "author": "J.R.R. Tolkien",
      "books": {
        "fellowship": {
          "title": "The Fellowship of the Ring",
          "chapters": 24,
          "published": "1954"
        },
        "two-towers": {
          "title": "The Two Towers",
          "chapters": 21,
          "published": "1954"
        },
        "return-king": {
          "title": "The Return of the King",
          "chapters": 20,
          "published": "1955"
        }
      }
    },
    "wheel-of-time": {
      "title": "Wheel of Time",
      "author": "Robert Jordan",
      "books": {
        "eye-of-world": {
          "title": "The Eye of the World",
          "chapters": 53,
          "published": "1990"
        },
        "great-hunt": {
          "title": "The Great Hunt",
          "chapters": 50,
          "published": "1990"
        },
        "dragon-reborn": {
          "title": "The Dragon Reborn",
          "chapters": 56,
          "published": "1991"
        }
      }
    },
    "song-ice-fire": {
      "title": "A Song of Ice and Fire",
      "author": "George R.R. Martin",
      "books": {
        "game-of-thrones": {
          "title": "A Game of Thrones",
          "chapters": 73,
          "published": "1996"
        },
        "clash-of-kings": {
          "title": "A Clash of Kings",
          "chapters": 70,
          "published": "1998"
        },
        "storm-of-swords": {
          "title": "A Storm of Swords",
          "chapters": 82,
          "published": "2000"
        },
        "feast-for-crows": {
          "title": "A Feast for Crows",
          "chapters": 46,
          "published": "2005"
        },
        "dance-with-dragons": {
          "title": "A Dance with Dragons",
          "chapters": 73,
          "published": "2011"
        }
      }
    }
  }
}
