{
  "book": {
    "title": "Mistborn: The Final Empire",
    "totalChapters": 38,
    "affiliateLink": "https://www.amazon.com/dp/0765350386?tag=profitfirstre-20"
  },
  "characters": [
    {
      "name": "Vin",
      "firstAppearance": 1,
      "featuredIn": [
        1,
        2,
        3,
        4,
        5,
        6,
        7,
        8,
        9,
        10,
        11,
        12,
        13,
        14,
        15,
        16,
        17,
        18,
        19,
        20,
        21,
        22,
        23,
        24,
        25,
        26,
        27,
        28,
        29,
        30,
        31,
        32,
        33,
        34,
        35,
        36,
        37,
        38
      ],
      "descriptions": [
        {
          "startChapter": 1,
          "endChapter": 5,
          "text": "Vin is a wary street orphan surviving in Luthadel\u2019s criminal underworld, unsure why odd strokes of 'luck' seem to follow her."
        },
        {
          "startChapter": 6,
          "endChapter": 15,
          "text": "Vin starts to find people she might trust, though her guarded nature remains."
        },
        {
          "startChapter": 16,
          "endChapter": 30,
          "text": "She becomes more confident and begins to accept her place in something larger."
        },
        {
          "startChapter": 31,
          "endChapter": 38,
          "text": "Vin grows into a key figure, with her strength and determination shaping events."
        }
      ]
    },
    {
      "name": "Kelsier",
      "firstAppearance": 1,
      "featuredIn": [
        2,
        3,
        4,
        5,
        6,
        7,
        8,
        9,
        10,
        11,
        12,
        13,
        14,
        15,
        16
      ],
      "descriptions": [
        {
          "startChapter": 1,
          "endChapter": 5,
          "text": "Kelsier is a daring figure with a mischievous grin, known for surviving the impossible."
        },
        {
          "startChapter": 6,
          "endChapter": 15,
          "text": "His charm and confidence draw together an unusual crew."
        },
        {
          "startChapter": 16,
          "endChapter": 30,
          "text": "Kelsier\u2019s rebellious nature inspires those around him."
        },
        {
          "startChapter": 31,
          "endChapter": 38,
          "text": "His legend looms larger than life as the story reaches its climax."
        }
      ]
    },
    {
      "name": "Elend Venture",
      "firstAppearance": 1,
      "featuredIn": [
        8,
        9,
        10,
        11,
        12,
        13,
        14,
        15,
        16,
        17,
        18,
        19,
        20,
        21,
        22,
        23,
        24,
        25,
        26,
        27,
        28,
        29,
        30,
        31,
        32,
        33,
        34,
        35,
        36,
        37,
        38
      ],
      "descriptions": [
        {
          "startChapter": 1,
          "endChapter": 5,
          "text": "Elend Venture is a thoughtful young nobleman, more interested in books than parties."
        },
        {
          "startChapter": 6,
          "endChapter": 15,
          "text": "His curiosity sets him apart from his peers."
        },
        {
          "startChapter": 16,
          "endChapter": 30,
          "text": "Elend\u2019s ideals begin to challenge the world he knows."
        },
        {
          "startChapter": 31,
          "endChapter": 38,
          "text": "He grows into a man whose choices truly matter."
        }
      ]
    },
    {
      "name": "Sazed",
      "firstAppearance": 1,
      "featuredIn": [
        5,
        6,
        7,
        8,
        9,
        10,
        11,
        12,
        13,
        14,
        15,
        16,
        17,
        18,
        19,
        20,
        21,
        22,
        23,
        24,
        25,
        26,
        27,
        28,
        29,
        30,
        31,
        32,
        33,
        34,
        35,
        36,
        37,
        38
      ],
      "descriptions": [
        {
          "startChapter": 1,
          "endChapter": 5,
          "text": "Sazed is a calm, soft-spoken man with a deep respect for learning."
        },
        {
          "startChapter": 6,
          "endChapter": 15,
          "text": "His quiet wisdom makes him a steady presence to those he aids."
        },
        {
          "startChapter": 16,
          "endChapter": 30,
          "text": "Sazed\u2019s knowledge and patience help guide his companions."
        },
        {
          "startChapter": 31,
          "endChapter": 38,
          "text": "His role as a teacher and advisor becomes all the more vital."
        }
      ]
    },
    {
      "name": "Breeze",
      "firstAppearance": 1,
      "featuredIn": [
        3,
        4,
        5,
        6,
        7,
        8,
        9,
        10,
        11,
        12,
        13,
        14,
        15,
        16,
        17,
        18,
        19,
        20,
        21,
        22,
        23,
        24,
        25,
        26,
        27,
        28,
        29,
        30,
        31,
        32,
        33,
        34,
        35,
        36,
        37,
        38
      ],
      "descriptions": [
        {
          "startChapter": 1,
          "endChapter": 5,
          "text": "Breeze is a refined, witty man who enjoys comfort and clever words."
        },
        {
          "startChapter": 6,
          "endChapter": 15,
          "text": "He lends a touch of charm and levity to the crew."
        },
        {
          "startChapter": 16,
          "endChapter": 30,
          "text": "Breeze\u2019s smooth demeanor helps soothe difficult situations."
        },
        {
          "startChapter": 31,
          "endChapter": 38,
          "text": "His cleverness and calm presence remain invaluable."
        }
      ]
    },
    {
      "name": "Clubs",
      "firstAppearance": 1,
      "featuredIn": [
        3,
        4,
        5,
        6,
        7,
        8,
        9,
        10,
        11,
        12,
        13,
        14,
        15,
        16,
        17,
        18,
        19,
        20,
        21,
        22,
        23,
        24,
        25,
        26,
        27,
        28,
        29,
        30,
        31,
        32,
        33,
        34,
        35,
        36,
        37,
        38
      ],
      "descriptions": [
        {
          "startChapter": 1,
          "endChapter": 5,
          "text": "Clubs is a gruff, practical craftsman who doesn\u2019t waste words."
        },
        {
          "startChapter": 6,
          "endChapter": 15,
          "text": "He provides a safe base for the crew and keeps them grounded."
        },
        {
          "startChapter": 16,
          "endChapter": 30,
          "text": "Clubs\u2019 no-nonsense attitude hides a reliable heart."
        },
        {
          "startChapter": 31,
          "endChapter": 38,
          "text": "He continues to support the crew through every challenge."
        }
      ]
    },
    {
      "name": "Spook",
      "firstAppearance": 1,
      "featuredIn": [
        3,
        4,
        5,
        6,
        7,
        8,
        9,
        10,
        11,
        12,
        13,
        14,
        15,
        16,
        17,
        18,
        19,
        20,
        21,
        22,
        23,
        24,
        25,
        26,
        27,
        28,
        29,
        30,
        31,
        32,
        33,
        34,
        35,
        36,
        37,
        38
      ],
      "descriptions": [
        {
          "startChapter": 1,
          "endChapter": 5,
          "text": "Spook is the youngest member of the crew, eager to prove himself."
        },
        {
          "startChapter": 6,
          "endChapter": 15,
          "text": "His youthful energy and slang bring a unique voice to the group."
        },
        {
          "startChapter": 16,
          "endChapter": 30,
          "text": "Spook becomes more involved as trust grows."
        },
        {
          "startChapter": 31,
          "endChapter": 38,
          "text": "His presence remains a light in darker moments."
        }
      ]
    },
    {
      "name": "Dockson",
      "firstAppearance": 1,
      "featuredIn": [
        3,
        4,
        5,
        6,
        7,
        8,
        9,
        10,
        11,
        12,
        13,
        14,
        15,
        16,
        17,
        18,
        19,
        20,
        21,
        22,
        23,
        24,
        25,
        26,
        27,
        28,
        29,
        30,
        31,
        32,
        33,
        34,
        35,
        36,
        37,
        38
      ],
      "descriptions": [
        {
          "startChapter": 1,
          "endChapter": 5,
          "text": "Dockson is Kelsier\u2019s organized and reliable right hand."
        },
        {
          "startChapter": 6,
          "endChapter": 15,
          "text": "He manages the crew\u2019s plans with efficiency and care."
        },
        {
          "startChapter": 16,
          "endChapter": 30,
          "text": "Dockson\u2019s practicality keeps the crew on track."
        },
        {
          "startChapter": 31,
          "endChapter": 38,
          "text": "He continues to hold things together as tensions rise."
        }
      ]
    },
    {
      "name": "Ham",
      "firstAppearance": 1,
      "featuredIn": [
        3,
        4,
        5,
        6,
        7,
        8,
        9,
        10,
        11,
        12,
        13,
        14,
        15,
        16,
        17,
        18,
        19,
        20,
        21,
        22,
        23,
        24,
        25,
        26,
        27,
        28,
        29,
        30,
        31,
        32,
        33,
        34,
        35,
        36,
        37,
        38
      ],
      "descriptions": [
        {
          "startChapter": 1,
          "endChapter": 5,
          "text": "Ham is a friendly, muscular man with a surprising love of philosophy."
        },
        {
          "startChapter": 6,
          "endChapter": 15,
          "text": "He mixes good-natured debates with a readiness to act."
        },
        {
          "startChapter": 16,
          "endChapter": 30,
          "text": "Ham\u2019s thoughtful strength makes him a steady ally."
        },
        {
          "startChapter": 31,
          "endChapter": 38,
          "text": "His loyalty to his friends is never in doubt."
        }
      ]
    },
    {
      "name": "Marsh",
      "firstAppearance": 1,
      "featuredIn": [
        3,
        4,
        5,
        6,
        7,
        8,
        9,
        10,
        11,
        12,
        13,
        14,
        15,
        16,
        17,
        18,
        19,
        20,
        21,
        22,
        23,
        24,
        25,
        26,
        27,
        28,
        29,
        30,
        31,
        32,
        33,
        34,
        35,
        36,
        37,
        38
      ],
      "descriptions": [
        {
          "startChapter": 1,
          "endChapter": 5,
          "text": "Marsh is Kelsier\u2019s older brother, serious and quiet where Kelsier is brash."
        },
        {
          "startChapter": 6,
          "endChapter": 15,
          "text": "His dedication runs deep, even when unspoken."
        },
        {
          "startChapter": 16,
          "endChapter": 30,
          "text": "Marsh\u2019s persistence becomes an asset to the crew."
        },
        {
          "startChapter": 31,
          "endChapter": 38,
          "text": "He continues to play a part as the struggle escalates."
        }
      ]
    },
    {
      "name": "Lord Ruler",
      "firstAppearance": 1,
      "featuredIn": [
        1,
        2,
        3,
        4,
        5,
        6,
        7,
        8,
        9,
        10,
        11,
        12,
        13,
        14,
        15,
        16,
        17,
        18,
        19,
        20,
        21,
        22,
        23,
        24,
        25,
        26,
        27,
        28,
        29,
        30,
        31,
        32,
        33,
        34,
        35,
        36,
        37,
        38
      ],
      "descriptions": [
        {
          "startChapter": 1,
          "endChapter": 5,
          "text": "The Lord Ruler is the distant, absolute ruler of the Final Empire, worshipped and feared as immortal."
        },
        {
          "startChapter": 6,
          "endChapter": 15,
          "text": "His reach touches every corner of society."
        },
        {
          "startChapter": 16,
          "endChapter": 30,
          "text": "His oppressive control weighs heavily on the land."
        },
        {
          "startChapter": 31,
          "endChapter": 38,
          "text": "The Lord Ruler remains a figure of awe and terror until the very end."
        }
      ]
    },
    {
      "name": "Straff Venture",
      "firstAppearance": 1,
      "featuredIn": [
        10,
        11,
        12,
        13,
        14,
        15,
        16,
        17,
        18,
        19,
        20
      ],
      "descriptions": [
        {
          "startChapter": 1,
          "endChapter": 5,
          "text": "Straff Venture is a powerful, ambitious nobleman at the head of House Venture."
        },
        {
          "startChapter": 6,
          "endChapter": 15,
          "text": "His influence casts a long shadow in Luthadel."
        },
        {
          "startChapter": 16,
          "endChapter": 30,
          "text": "Straff\u2019s hunger for power shapes many events."
        },
        {
          "startChapter": 31,
          "endChapter": 38,
          "text": "His ruthless nature only deepens as conflicts rise."
        }
      ]
    },
    {
      "name": "Reen",
      "firstAppearance": 1,
      "featuredIn": [
        1,
        2,
        3,
        4,
        5,
        6,
        7,
        8,
        9,
        10,
        11,
        12,
        13,
        14,
        15,
        16,
        17,
        18,
        19,
        20,
        21,
        22,
        23,
        24,
        25,
        26,
        27,
        28,
        29,
        30,
        31,
        32,
        33,
        34,
        35,
        36,
        37,
        38
      ],
      "descriptions": [
        {
          "startChapter": 1,
          "endChapter": 5,
          "text": "Reen is Vin\u2019s older brother, the one voice from her past that still echoes in her mind."
        },
        {
          "startChapter": 6,
          "endChapter": 15,
          "text": "His harsh lessons of survival linger over her thoughts."
        },
        {
          "startChapter": 16,
          "endChapter": 30,
          "text": "Reen\u2019s absence is felt as Vin builds a new life."
        },
        {
          "startChapter": 31,
          "endChapter": 38,
          "text": "His warnings continue to shape how she sees the world."
        }
      ]
    },
    {
      "name": "Kar",
      "firstAppearance": 1,
      "featuredIn": [
        15,
        16,
        17,
        18,
        19,
        20,
        21,
        22,
        23,
        24,
        25,
        26,
        27,
        28,
        29,
        30,
        31,
        32,
        33,
        34,
        35,
        36,
        37,
        38
      ],
      "descriptions": [
        {
          "startChapter": 1,
          "endChapter": 5,
          "text": "Kar is a brutish Inquisitor, one of the Lord Ruler\u2019s feared enforcers. His appearances are menacing and violent."
        },
        {
          "startChapter": 6,
          "endChapter": 15,
          "text": "Kar is a brutish Inquisitor, one of the Lord Ruler\u2019s feared enforcers. Kar embodies the terror of the Inquisitors."
        },
        {
          "startChapter": 16,
          "endChapter": 30,
          "text": "Kar is a brutish Inquisitor, one of the Lord Ruler\u2019s feared enforcers. His presence signals danger."
        },
        {
          "startChapter": 31,
          "endChapter": 38,
          "text": "Kar is a brutish Inquisitor, one of the Lord Ruler\u2019s feared enforcers. He is an enduring symbol of the empire\u2019s brutality."
        }
      ]
    },
    {
      "name": "Captain Demoux",
      "firstAppearance": 1,
      "featuredIn": [
        8,
        9,
        10,
        11,
        12,
        13,
        14,
        15,
        16,
        17,
        18,
        19,
        20,
        21,
        22,
        23,
        24,
        25,
        26,
        27,
        28,
        29,
        30,
        31,
        32,
        33,
        34,
        35,
        36,
        37,
        38
      ],
      "descriptions": [
        {
          "startChapter": 1,
          "endChapter": 5,
          "text": "Captain Demoux is a soldier who fights for the rebellion. Loyal and steady, he follows orders without complaint."
        },
        {
          "startChapter": 6,
          "endChapter": 15,
          "text": "Captain Demoux is a soldier who fights for the rebellion. He earns the trust of the crew."
        },
        {
          "startChapter": 16,
          "endChapter": 30,
          "text": "Captain Demoux is a soldier who fights for the rebellion. Demoux becomes a key figure in the Survivor\u2019s forces."
        },
        {
          "startChapter": 31,
          "endChapter": 38,
          "text": "Captain Demoux is a soldier who fights for the rebellion. His loyalty and honor never falter."
        }
      ]
    },
    {
      "name": "Lord Venture",
      "firstAppearance": 1,
      "featuredIn": [
        8,
        9,
        10,
        11,
        12,
        13,
        14,
        15,
        16,
        17,
        18,
        19,
        20,
        21,
        22,
        23,
        24,
        25,
        26,
        27,
        28,
        29,
        30,
        31,
        32,
        33,
        34,
        35,
        36,
        37,
        38
      ],
      "descriptions": [
        {
          "startChapter": 1,
          "endChapter": 5,
          "text": "Lord Venture is the head of House Venture, a powerful noble house. He oversees his house\u2019s vast influence."
        },
        {
          "startChapter": 6,
          "endChapter": 15,
          "text": "Lord Venture is the head of House Venture, a powerful noble house. His political maneuvering affects the rebellion\u2019s plans."
        },
        {
          "startChapter": 16,
          "endChapter": 30,
          "text": "Lord Venture is the head of House Venture, a powerful noble house. Venture remains a symbol of noble power."
        },
        {
          "startChapter": 31,
          "endChapter": 38,
          "text": "Lord Venture is the head of House Venture, a powerful noble house. His position defines much of the noble conflict."
        }
      ]
    },
    {
      "name": "Yeden",
      "firstAppearance": 1,
      "featuredIn": [
        3,
        4,
        5,
        6,
        7,
        8,
        9,
        10,
        11,
        12,
        13,
        14,
        15,
        16,
        17,
        18,
        19,
        20
      ],
      "descriptions": [
        {
          "startChapter": 1,
          "endChapter": 5,
          "text": "Yeden is a determined rebel leader desperate to see the skaa rise."
        },
        {
          "startChapter": 6,
          "endChapter": 15,
          "text": "He places his hopes in an unlikely alliance."
        },
        {
          "startChapter": 16,
          "endChapter": 30,
          "text": "Yeden\u2019s fervor pushes the rebellion forward."
        },
        {
          "startChapter": 31,
          "endChapter": 38,
          "text": "His unwavering belief carries heavy consequences."
        }
      ]
    }
  ],
  "recaps": {
    "1": "Spoiler-free recap for Chapter 1.",
    "2": "Spoiler-free recap for Chapter 2.",
    "3": "Spoiler-free recap for Chapter 3.",
    "4": "Spoiler-free recap for Chapter 4.",
    "5": "Spoiler-free recap for Chapter 5.",
    "6": "Spoiler-free recap for Chapter 6.",
    "7": "Spoiler-free recap for Chapter 7.",
    "8": "Spoiler-free recap for Chapter 8.",
    "9": "Spoiler-free recap for Chapter 9.",
    "10": "Spoiler-free recap for Chapter 10.",
    "11": "Spoiler-free recap for Chapter 11.",
    "12": "Spoiler-free recap for Chapter 12.",
    "13": "Spoiler-free recap for Chapter 13.",
    "14": "Spoiler-free recap for Chapter 14.",
    "15": "Spoiler-free recap for Chapter 15.",
    "16": "Spoiler-free recap for Chapter 16.",
    "17": "Spoiler-free recap for Chapter 17.",
    "18": "Spoiler-free recap for Chapter 18.",
    "19": "Spoiler-free recap for Chapter 19.",
    "20": "Spoiler-free recap for Chapter 20.",
    "21": "Spoiler-free recap for Chapter 21.",
    "22": "Spoiler-free recap for Chapter 22.",
    "23": "Spoiler-free recap for Chapter 23.",
    "24": "Spoiler-free recap for Chapter 24.",
    "25": "Spoiler-free recap for Chapter 25.",
    "26": "Spoiler-free recap for Chapter 26.",
    "27": "Spoiler-free recap for Chapter 27.",
    "28": "Spoiler-free recap for Chapter 28.",
    "29": "Spoiler-free recap for Chapter 29.",
    "30": "Spoiler-free recap for Chapter 30.",
    "31": "Spoiler-free recap for Chapter 31.",
    "32": "Spoiler-free recap for Chapter 32.",
    "33": "Spoiler-free recap for Chapter 33.",
    "34": "Spoiler-free recap for Chapter 34.",
    "35": "Spoiler-free recap for Chapter 35.",
    "36": "Spoiler-free recap for Chapter 36.",
    "37": "Spoiler-free recap for Chapter 37.",
    "38": "Spoiler-free recap for Chapter 38."
  }
}