{
  "book": {
    "title": "The Way of Kings",
    "totalChapters": 3,
    "affiliateLink": "https://www.amazon.com/dp/0765326353?tag=profitfirstre-20",
    "theme": {
      "primaryColor": "text-blue-800",
      "underlineColor": "border-yellow-400",
      "backgroundEffect": "stormlight-glow"
    }
  },
  "characters": [],
  "recaps": {
    "1": "Spoiler-free recap for Stormlight Chapter 1",
    "2": "Spoiler-free recap for Stormlight Chapter 2",
    "3": "Spoiler-free recap for Stormlight Chapter 3"
  }
}